gomailer/__init__.py
gomailer/automation.py
gomailer/client.py
gomailer/contacts.py
gomailer/mailing.py
src/__init__.py
src/automation.py
src/client.py
src/contacts.py
src/mailing.py
gomailer-1.0.3.dist-info/METADATA
gomailer-1.0.3.dist-info/WHEEL
gomailer-1.0.3.dist-info/top_level.txt
gomailer-1.0.3.dist-info/RECORD
