Metadata-Version: 2.1
Name: gomailer
Version: 1.0.3
Summary: The Go-Mailer Utility library
Home-page: UNKNOWN
Author: Go-Mailer Limited
Author-email: info@go-mailer.com
License: UNKNOWN
Platform: UNKNOWN
Classifier: Programming Language :: Python :: 3
Classifier: License :: OSI Approved :: MIT License
Classifier: Operating System :: OS Independent
Requires-Python: >=3.6
